ids_rs-1.0.0.dist-info/METADATA
ids_rs-1.0.0.dist-info/WHEEL
ids_rs/schemas/bef.json
ids_rs/schemas/lpr3_kontakter.json
ids_rs/schemas/uddf.json
ids_rs/schemas/lpr3_diagnoser.json
ids_rs/schemas/ind.json
ids_rs/schemas/lpr_adm.json
ids_rs/schemas/idan.json
ids_rs/schemas/lpr_bes.json
ids_rs/schemas/akm.json
ids_rs/schemas/lpr_diag.json
ids_rs/__init__.py
ids_rs/mappings/hustype.json
ids_rs/mappings/icd10.json
ids_rs/mappings/civst.json
ids_rs/mappings/fm_mark.json
ids_rs/mappings/beskst13.json
ids_rs/mappings/scd.json
ids_rs/mappings/socio13.json
ids_rs/mappings/family_type.json
ids_rs/mappings/plads.json
ids_rs/mappings/hfaudd.json
ids_rs/mappings/statsb.json
ids_rs/mappings/tilknyt.json
ids_rs/mappings/jobkat.json
ids_rs/mappings/pre_socio.json
ids_rs/mappings/reg.json
ids_rs-1.0.0.data/scripts/ids
ids_rs.libs/libbrotlicommon-a91ead09.so.1
ids_rs.libs/libbrotlidec-64d8a501.so.1
ids_rs.libs/libbz2-218c4abd.so.1.0
ids_rs.libs/libfontconfig-a94b4059.so.1
ids_rs.libs/libfreetype-fd0e5281.so.6
ids_rs.libs/libpng16-29896eea.so.16
ids_rs-1.0.0.dist-info/RECORD
