Metadata-Version: 2.4
Name: ids-rs
Version: 1.0.0
Classifier: Programming Language :: Rust
Classifier: Programming Language :: Python :: 3
Classifier: Programming Language :: Python :: 3.7
Classifier: Programming Language :: Python :: 3.8
Classifier: Programming Language :: Python :: 3.9
Classifier: Programming Language :: Python :: 3.10
Classifier: Programming Language :: Python :: 3.11
Classifier: Environment :: Console
Classifier: Intended Audience :: Science/Research
Summary: Incidence Density Sampling CLI Tool
Author-email: Tobias Kragholm <tkragholm@gmail.com>
License: MIT
Requires-Python: >=3.7
